rogues/__init__.py
rogues/matrices/__init__.py
rogues/matrices/cauchy.py
rogues/matrices/chebspec.py
rogues/matrices/chebvand.py
rogues/matrices/chow.py
rogues/matrices/clement.py
rogues/matrices/comp.py
rogues/matrices/compan.py
rogues/matrices/condex.py
rogues/matrices/cycol.py
rogues/matrices/dingdong.py
rogues/matrices/dorr.py
rogues/matrices/dramadah.py
rogues/matrices/fiedler.py
rogues/matrices/forsythe.py
rogues/matrices/frank.py
rogues/matrices/gearm.py
rogues/matrices/gfpp.py
rogues/matrices/grcar.py
rogues/matrices/hadamard.py
rogues/matrices/hankel.py
rogues/matrices/hanowa.py
rogues/matrices/hilb.py
rogues/matrices/invhess.py
rogues/matrices/invol.py
rogues/matrices/ipjfact.py
rogues/matrices/jordbloc.py
rogues/matrices/kahan.py
rogues/matrices/kms.py
rogues/matrices/krylov.py
rogues/matrices/lauchli.py
rogues/matrices/lehmer.py
rogues/matrices/lesp.py
rogues/matrices/lotkin.py
rogues/matrices/minij.py
rogues/matrices/moler.py
rogues/matrices/neumann.py
rogues/matrices/ohess.py
rogues/matrices/parter.py
rogues/matrices/pascal.py
rogues/matrices/pdtoep.py
rogues/matrices/pei.py
rogues/matrices/pentoep.py
rogues/matrices/poisson.py
rogues/matrices/prolate.py
rogues/matrices/qmult.py
rogues/matrices/rando.py
rogues/matrices/randsvd.py
rogues/matrices/redheff.py
rogues/matrices/riemann.py
rogues/matrices/smoke.py
rogues/matrices/triw.py
rogues/matrices/wathen.py
rogues/matrices/wilk.py
rogues/matrices/wilkinson.py
rogues/utils/__init__.py
rogues/utils/augment.py
rogues/utils/bandred.py
rogues/utils/cgs.py
rogues/utils/cond.py
rogues/utils/condeig.py
rogues/utils/cpltaxes.py
rogues/utils/dual.py
rogues/utils/fv.py
rogues/utils/ge.py
rogues/utils/gersh.py
rogues/utils/hankel.py
rogues/utils/house.py
rogues/utils/mdsmax.py
rogues/utils/mgs.py
rogues/utils/pow2.py
rogues/utils/ps.py
rogues/utils/pscont.py
rogues/utils/repmat.py
rogues/utils/rq.py
rogues/utils/skewpart.py
rogues/utils/sparsify.py
rogues/utils/sub.py
rogues/utils/symmpart.py
rogues-1.0.1.dist-info/METADATA
rogues-1.0.1.dist-info/WHEEL
rogues-1.0.1.dist-info/top_level.txt
rogues-1.0.1.dist-info/zip-safe
rogues-1.0.1.dist-info/RECORD
