Metadata-Version: 2.1
Name: rogues
Version: 1.0.1
Summary: Python and numpy port of Nicholas Higham's m*lab test matrices
Home-page: https://github.com/macd/rogues
Author: Don MacMillen
Author-email: don@macmillen.net
License: MIT
Keywords: numpy scipy matplotlib linalg
Classifier: Development Status :: 4 - Beta
Classifier: Intended Audience :: Developers
Classifier: Intended Audience :: Science/Research
Classifier: License :: OSI Approved :: MIT License
Classifier: Operating System :: OS Independent
Classifier: Topic :: Scientific/Engineering :: Mathematics
Requires-Dist: numpy
Requires-Dist: scipy
